{
  "annotations": {
    "list": [
      {
        "builtIn": 1,
        "datasource": {
          "type": "datasource",
          "uid": "grafana"
        },
        "enable": true,
        "hide": true,
        "iconColor": "rgba(0, 211, 255, 1)",
        "name": "Annotations & Alerts",
        "type": "dashboard"
      }
    ]
  },
  "editable": true,
  "fiscalYearStartMonth": 0,
  "graphTooltip": 1,
  "id": 1968044124213248,
  "links": [],
  "panels": [
    {
      "datasource": {
        "type": "prometheus",
        "uid": "PAE45454D0EDB9216"
      },
      "fieldConfig": {
        "defaults": {
          "color": {
            "mode": "palette-classic"
          },
          "mappings": [],
          "thresholds": {
            "mode": "absolute",
            "steps": [
              {
                "color": "green",
                "value": 0
              },
              {
                "color": "red",
                "value": 80
              }
            ]
          }
        },
        "overrides": []
      },
      "gridPos": {
        "h": 3,
        "w": 24,
        "x": 0,
        "y": 0
      },
      "id": 8,
      "options": {
        "dataLinks": [],
        "displayMode": "gradient",
        "legend": {
          "calcs": [
            "lastNotNull"
          ],
          "displayMode": "table",
          "placement": "right",
          "showLegend": true
        },
        "maxVizHeight": 300,
        "minVizHeight": 16,
        "minVizWidth": 8,
        "namePlacement": "auto",
        "orientation": "auto",
        "reduceOptions": {
          "calcs": [
            "lastNotNull"
          ],
          "fields": "",
          "values": false
        },
        "showUnfilled": true,
        "sizing": "auto",
        "valueMode": "color"
      },
      "pluginVersion": "12.2.0-16636675413",
      "targets": [
        {
          "datasource": {
            "type": "prometheus",
            "uid": "PAE45454D0EDB9216"
          },
          "expr": "avg(apache_uptime_seconds_total{namespace=~\"^$namespace\"}) by (namespace,pod)",
          "format": "time_series",
          "intervalFactor": 2,
          "legendFormat": "{{namespace}} - {{pod}}",
          "refId": "A",
          "step": 1800
        }
      ],
      "title": "Uptime",
      "type": "bargauge"
    },
    {
      "datasource": {
        "type": "prometheus",
        "uid": "PAE45454D0EDB9216"
      },
      "fieldConfig": {
        "defaults": {
          "color": {
            "mode": "palette-classic"
          },
          "custom": {
            "axisBorderShow": false,
            "axisCenteredZero": false,
            "axisColorMode": "text",
            "axisLabel": "",
            "axisPlacement": "auto",
            "barAlignment": 0,
            "barWidthFactor": 0.6,
            "drawStyle": "line",
            "fillOpacity": 0,
            "gradientMode": "none",
            "hideFrom": {
              "legend": false,
              "tooltip": false,
              "viz": false
            },
            "insertNulls": false,
            "lineInterpolation": "linear",
            "lineWidth": 2,
            "pointSize": 5,
            "scaleDistribution": {
              "type": "linear"
            },
            "showPoints": "never",
            "spanNulls": false,
            "stacking": {
              "group": "A",
              "mode": "none"
            },
            "thresholdsStyle": {
              "mode": "off"
            }
          },
          "mappings": [],
          "max": 1,
          "thresholds": {
            "mode": "absolute",
            "steps": [
              {
                "color": "green",
                "value": 0
              },
              {
                "color": "red",
                "value": 80
              }
            ]
          },
          "unit": "short"
        },
        "overrides": []
      },
      "gridPos": {
        "h": 7,
        "w": 24,
        "x": 0,
        "y": 3
      },
      "id": 5,
      "options": {
        "dataLinks": [],
        "legend": {
          "calcs": [
            "lastNotNull"
          ],
          "displayMode": "table",
          "placement": "right",
          "showLegend": true
        },
        "tooltip": {
          "hideZeros": false,
          "mode": "multi",
          "sort": "none"
        }
      },
      "pluginVersion": "12.2.0-16636675413",
      "targets": [
        {
          "datasource": {
            "type": "prometheus",
            "uid": "PAE45454D0EDB9216"
          },
          "expr": "count(apache_up{namespace=~\"^$namespace\"} == 1) by (pod)",
          "format": "time_series",
          "intervalFactor": 2,
          "legendFormat": "Up - {{pod}}",
          "refId": "A",
          "step": 120
        }
      ],
      "title": "Apache Up / Down",
      "type": "timeseries"
    },
    {
      "datasource": {
        "type": "prometheus",
        "uid": "PAE45454D0EDB9216"
      },
      "fieldConfig": {
        "defaults": {
          "color": {
            "mode": "palette-classic"
          },
          "custom": {
            "axisBorderShow": false,
            "axisCenteredZero": false,
            "axisColorMode": "text",
            "axisLabel": "",
            "axisPlacement": "auto",
            "barAlignment": 0,
            "barWidthFactor": 0.6,
            "drawStyle": "line",
            "fillOpacity": 10,
            "gradientMode": "none",
            "hideFrom": {
              "legend": false,
              "tooltip": false,
              "viz": false
            },
            "insertNulls": false,
            "lineInterpolation": "linear",
            "lineWidth": 1,
            "pointSize": 5,
            "scaleDistribution": {
              "type": "linear"
            },
            "showPoints": "never",
            "spanNulls": false,
            "stacking": {
              "group": "A",
              "mode": "none"
            },
            "thresholdsStyle": {
              "mode": "off"
            }
          },
          "mappings": [],
          "thresholds": {
            "mode": "absolute",
            "steps": [
              {
                "color": "green",
                "value": 0
              },
              {
                "color": "red",
                "value": 80
              }
            ]
          },
          "unit": "deckbytes"
        },
        "overrides": []
      },
      "gridPos": {
        "h": 10,
        "w": 12,
        "x": 0,
        "y": 10
      },
      "id": 3,
      "options": {
        "dataLinks": [],
        "legend": {
          "calcs": [
            "mean",
            "lastNotNull",
            "max",
            "min"
          ],
          "displayMode": "table",
          "placement": "bottom",
          "showLegend": true
        },
        "tooltip": {
          "hideZeros": false,
          "mode": "multi",
          "sort": "none"
        }
      },
      "pluginVersion": "12.2.0-16636675413",
      "targets": [
        {
          "datasource": {
            "type": "prometheus",
            "uid": "PAE45454D0EDB9216"
          },
          "expr": "rate(apache_sent_kilobytes_total{namespace=~\"^$namespace\"}[5m])",
          "format": "time_series",
          "intervalFactor": 2,
          "legendFormat": "{{namespace}} - {{pod}}",
          "refId": "A",
          "step": 240
        }
      ],
      "title": "Current total kbytes sent",
      "type": "timeseries"
    },
    {
      "datasource": {
        "type": "prometheus",
        "uid": "PAE45454D0EDB9216"
      },
      "fieldConfig": {
        "defaults": {
          "color": {
            "mode": "palette-classic"
          },
          "custom": {
            "axisBorderShow": false,
            "axisCenteredZero": false,
            "axisColorMode": "text",
            "axisLabel": "",
            "axisPlacement": "auto",
            "barAlignment": 0,
            "barWidthFactor": 0.6,
            "drawStyle": "line",
            "fillOpacity": 0,
            "gradientMode": "none",
            "hideFrom": {
              "legend": false,
              "tooltip": false,
              "viz": false
            },
            "insertNulls": false,
            "lineInterpolation": "linear",
            "lineWidth": 1,
            "pointSize": 5,
            "scaleDistribution": {
              "type": "linear"
            },
            "showPoints": "never",
            "spanNulls": false,
            "stacking": {
              "group": "A",
              "mode": "none"
            },
            "thresholdsStyle": {
              "mode": "off"
            }
          },
          "mappings": [],
          "thresholds": {
            "mode": "absolute",
            "steps": [
              {
                "color": "green",
                "value": 0
              },
              {
                "color": "red",
                "value": 80
              }
            ]
          },
          "unit": "short"
        },
        "overrides": []
      },
      "gridPos": {
        "h": 10,
        "w": 12,
        "x": 12,
        "y": 10
      },
      "id": 1,
      "options": {
        "dataLinks": [],
        "legend": {
          "calcs": [
            "mean",
            "lastNotNull",
            "max",
            "min"
          ],
          "displayMode": "table",
          "placement": "bottom",
          "showLegend": true
        },
        "tooltip": {
          "hideZeros": false,
          "mode": "multi",
          "sort": "none"
        }
      },
      "pluginVersion": "12.2.0-16636675413",
      "targets": [
        {
          "datasource": {
            "type": "prometheus",
            "uid": "PAE45454D0EDB9216"
          },
          "expr": "rate(apache_accesses_total{namespace=~\"^$namespace\"}[5m])",
          "format": "time_series",
          "intervalFactor": 2,
          "legendFormat": "{{namespace}} - {{pod}}",
          "refId": "A",
          "step": 240
        }
      ],
      "title": "Current total apache accesses",
      "type": "timeseries"
    },
    {
      "datasource": {
        "type": "prometheus",
        "uid": "PAE45454D0EDB9216"
      },
      "fieldConfig": {
        "defaults": {
          "color": {
            "mode": "palette-classic"
          },
          "custom": {
            "axisBorderShow": false,
            "axisCenteredZero": false,
            "axisColorMode": "text",
            "axisLabel": "",
            "axisPlacement": "auto",
            "barAlignment": 0,
            "barWidthFactor": 0.6,
            "drawStyle": "line",
            "fillOpacity": 0,
            "gradientMode": "none",
            "hideFrom": {
              "legend": false,
              "tooltip": false,
              "viz": false
            },
            "insertNulls": false,
            "lineInterpolation": "linear",
            "lineWidth": 1,
            "pointSize": 5,
            "scaleDistribution": {
              "type": "linear"
            },
            "showPoints": "never",
            "spanNulls": false,
            "stacking": {
              "group": "A",
              "mode": "none"
            },
            "thresholdsStyle": {
              "mode": "off"
            }
          },
          "mappings": [],
          "thresholds": {
            "mode": "absolute",
            "steps": [
              {
                "color": "green",
                "value": 0
              },
              {
                "color": "red",
                "value": 80
              }
            ]
          },
          "unit": "short"
        },
        "overrides": []
      },
      "gridPos": {
        "h": 10,
        "w": 24,
        "x": 0,
        "y": 20
      },
      "id": 2,
      "options": {
        "dataLinks": [],
        "legend": {
          "calcs": [
            "mean",
            "lastNotNull",
            "max",
            "min"
          ],
          "displayMode": "table",
          "placement": "right",
          "showLegend": true
        },
        "tooltip": {
          "hideZeros": false,
          "mode": "multi",
          "sort": "none"
        }
      },
      "pluginVersion": "12.2.0-16636675413",
      "targets": [
        {
          "datasource": {
            "type": "prometheus",
            "uid": "PAE45454D0EDB9216"
          },
          "expr": "apache_scoreboard{namespace=~\"^$namespace\",state=~\"^$state\"}",
          "format": "time_series",
          "intervalFactor": 2,
          "legendFormat": "{{namespace}} - {{pod}} - {{ state }}",
          "refId": "A",
          "step": 120
        }
      ],
      "title": "Apache scoreboard statuses",
      "type": "timeseries"
    },
    {
      "datasource": {
        "type": "prometheus",
        "uid": "PAE45454D0EDB9216"
      },
      "fieldConfig": {
        "defaults": {
          "color": {
            "mode": "palette-classic"
          },
          "custom": {
            "axisBorderShow": false,
            "axisCenteredZero": false,
            "axisColorMode": "text",
            "axisLabel": "",
            "axisPlacement": "auto",
            "barAlignment": 0,
            "barWidthFactor": 0.6,
            "drawStyle": "line",
            "fillOpacity": 0,
            "gradientMode": "none",
            "hideFrom": {
              "legend": false,
              "tooltip": false,
              "viz": false
            },
            "insertNulls": false,
            "lineInterpolation": "linear",
            "lineWidth": 1,
            "pointSize": 5,
            "scaleDistribution": {
              "type": "linear"
            },
            "showPoints": "never",
            "spanNulls": false,
            "stacking": {
              "group": "A",
              "mode": "none"
            },
            "thresholdsStyle": {
              "mode": "off"
            }
          },
          "mappings": [],
          "thresholds": {
            "mode": "absolute",
            "steps": [
              {
                "color": "green",
                "value": 0
              },
              {
                "color": "red",
                "value": 80
              }
            ]
          },
          "unit": "short"
        },
        "overrides": []
      },
      "gridPos": {
        "h": 10,
        "w": 12,
        "x": 0,
        "y": 30
      },
      "id": 7,
      "options": {
        "dataLinks": [],
        "legend": {
          "calcs": [
            "mean",
            "lastNotNull",
            "max",
            "min"
          ],
          "displayMode": "table",
          "placement": "right",
          "showLegend": true
        },
        "tooltip": {
          "hideZeros": false,
          "mode": "multi",
          "sort": "none"
        }
      },
      "pluginVersion": "12.2.0-16636675413",
      "targets": [
        {
          "datasource": {
            "type": "prometheus",
            "uid": "PAE45454D0EDB9216"
          },
          "expr": "apache_workers{namespace=~\"^$namespace\",state=~\"busy\"}\n",
          "format": "time_series",
          "intervalFactor": 2,
          "legendFormat": "{{namespace}} - {{pod}} - {{ state }}",
          "refId": "A",
          "step": 240
        },
        {
          "datasource": {
            "type": "prometheus",
            "uid": "PAE45454D0EDB9216"
          },
          "expr": "apache_workers{namespace=~\"^$namespace\",state=~\"idle\"}",
          "legendFormat": "{{namespace}} - {{pod}} - {{ state }}",
          "refId": "B"
        }
      ],
      "title": "Apache worker statuses",
      "type": "timeseries"
    },
    {
      "datasource": {
        "type": "prometheus",
        "uid": "PAE45454D0EDB9216"
      },
      "fieldConfig": {
        "defaults": {
          "color": {
            "mode": "palette-classic"
          },
          "custom": {
            "axisBorderShow": false,
            "axisCenteredZero": false,
            "axisColorMode": "text",
            "axisLabel": "",
            "axisPlacement": "auto",
            "barAlignment": 0,
            "barWidthFactor": 0.6,
            "drawStyle": "line",
            "fillOpacity": 10,
            "gradientMode": "none",
            "hideFrom": {
              "legend": false,
              "tooltip": false,
              "viz": false
            },
            "insertNulls": false,
            "lineInterpolation": "linear",
            "lineWidth": 1,
            "pointSize": 5,
            "scaleDistribution": {
              "type": "linear"
            },
            "showPoints": "never",
            "spanNulls": false,
            "stacking": {
              "group": "A",
              "mode": "none"
            },
            "thresholdsStyle": {
              "mode": "off"
            }
          },
          "mappings": [],
          "min": 0,
          "thresholds": {
            "mode": "absolute",
            "steps": [
              {
                "color": "green",
                "value": 0
              },
              {
                "color": "red",
                "value": 80
              }
            ]
          },
          "unit": "short"
        },
        "overrides": []
      },
      "gridPos": {
        "h": 10,
        "w": 12,
        "x": 12,
        "y": 30
      },
      "id": 4,
      "options": {
        "dataLinks": [],
        "legend": {
          "calcs": [
            "mean",
            "lastNotNull",
            "max",
            "min"
          ],
          "displayMode": "table",
          "placement": "bottom",
          "showLegend": true
        },
        "tooltip": {
          "hideZeros": false,
          "mode": "multi",
          "sort": "none"
        }
      },
      "pluginVersion": "12.2.0-16636675413",
      "targets": [
        {
          "datasource": {
            "type": "prometheus",
            "uid": "PAE45454D0EDB9216"
          },
          "expr": "apache_cpuload{namespace=~\"^$namespace\"}",
          "format": "time_series",
          "intervalFactor": 2,
          "legendFormat": "{{namespace}} - {{pod}}",
          "refId": "A",
          "step": 240
        }
      ],
      "title": "Apache CPU load",
      "type": "timeseries"
    }
  ],
  "preload": false,
  "refresh": "1m",
  "schemaVersion": 41,
  "tags": [],
  "templating": {
    "list": [
      {
        "current": {
          "text": "Mimir",
          "value": "PAE45454D0EDB9216"
        },
        "label": "datasource",
        "name": "DS_PROMETHEUS",
        "options": [],
        "query": "prometheus",
        "refresh": 1,
        "regex": "",
        "type": "datasource"
      },
      {
        "current": {
          "text": "All",
          "value": "$__all"
        },
        "datasource": "PAE45454D0EDB9216",
        "definition": "label_values(apache_up, namespace)",
        "includeAll": true,
        "label": "Namespace",
        "name": "namespace",
        "options": [],
        "query": "label_values(apache_up, namespace)",
        "refresh": 2,
        "regex": "",
        "sort": 1,
        "type": "query"
      },
      {
        "current": {
          "text": [
            "All"
          ],
          "value": [
            "$__all"
          ]
        },
        "datasource": "PAE45454D0EDB9216",
        "definition": "label_values(apache_scoreboard, state)",
        "includeAll": true,
        "label": "Scoreboard State",
        "multi": true,
        "name": "state",
        "options": [],
        "query": "label_values(apache_scoreboard, state)",
        "refresh": 1,
        "regex": "",
        "sort": 1,
        "type": "query"
      }
    ]
  },
  "time": {
    "from": "now-24h",
    "to": "now"
  },
  "timepicker": {},
  "timezone": "",
  "title": "Apache3asd",
  "uid": "fC2E-BxZk3",
  "version": 1
}